setup.py
objectbdd/__init__.py
objectbdd/scenario.py
objectbdd.egg-info/PKG-INFO
objectbdd.egg-info/SOURCES.txt
objectbdd.egg-info/dependency_links.txt
objectbdd.egg-info/top_level.txt