Metadata-Version: 1.0
Name: objectbdd
Version: 0.1.1
Summary: A simple tool for working through a BDD scenario with objects
Home-page: github.com/berlin-ab
Author: Adam Berlin
Author-email: berlin.ab+objectbdd@gmail.com
License: UNKNOWN
Platform: UNKNOWN
